{"buildingID":2,"toFloor":2,"id":146,"map_id":6,"x_coord":485.0,"y_coord":218.0,"z_coord":0.0,"x_univ":485.0,"y_univ":218.0,"z_univ":0.0,"g_scores":0.0,"h_scores":0.0,"f_scores":0.0,"adjacencies":[{"weight":1.0,"target":139},{"weight":1.0,"target":144},{"weight":1.0,"target":413},{"weight":1.0,"target":2115}]}{"buildingID":2,"toFloor":1,"id":413,"map_id":7,"x_coord":521.0,"y_coord":213.0,"z_coord":0.0,"x_univ":521.0,"y_univ":213.0,"z_univ":0.0,"g_scores":0.0,"h_scores":0.0,"f_scores":0.0,"adjacencies":[{"weight":1.0,"target":412},{"weight":1.0,"target":146},{"weight":1.0,"target":2115}]}{"buildingID":4,"toFloor":2,"id":796,"map_id":13,"x_coord":679.0,"y_coord":309.0,"z_coord":0.0,"x_univ":679.0,"y_univ":309.0,"z_univ":0.0,"g_scores":0.0,"h_scores":0.0,"f_scores":0.0,"adjacencies":[{"weight":1.0,"target":797},{"weight":1.0,"target":969},{"weight":1.0,"target":1049}]}{"buildingID":4,"toFloor":3,"id":969,"map_id":14,"x_coord":667.0,"y_coord":326.0,"z_coord":0.0,"x_univ":667.0,"y_univ":326.0,"z_univ":0.0,"g_scores":0.0,"h_scores":0.0,"f_scores":0.0,"adjacencies":[{"weight":1.0,"target":966},{"weight":1.0,"target":1049},{"weight":1.0,"target":796}]}{"buildingID":4,"toFloor":2,"id":1005,"map_id":15,"x_coord":89.0,"y_coord":225.0,"z_coord":0.0,"x_univ":89.0,"y_univ":225.0,"z_univ":0.0,"g_scores":0.0,"h_scores":0.0,"f_scores":0.0,"adjacencies":[{"weight":1.0,"target":1004},{"weight":1.0,"target":1072},{"weight":1.0,"target":2153}]}{"buildingID":4,"toFloor":1,"id":1049,"map_id":15,"x_coord":679.0,"y_coord":307.0,"z_coord":0.0,"x_univ":679.0,"y_univ":307.0,"z_univ":0.0,"g_scores":0.0,"h_scores":0.0,"f_scores":0.0,"adjacencies":[{"weight":1.0,"target":1048},{"weight":1.0,"target":796},{"weight":1.0,"target":969}]}{"buildingID":4,"toFloor":3,"id":1072,"map_id":14,"x_coord":101.0,"y_coord":248.0,"z_coord":0.0,"x_univ":101.0,"y_univ":248.0,"z_univ":0.0,"g_scores":0.0,"h_scores":0.0,"f_scores":0.0,"adjacencies":[{"weight":1.0,"target":1071},{"weight":1.0,"target":1005},{"weight":1.0,"target":2153}]}{"buildingID":5,"toFloor":-1,"id":1078,"map_id":17,"x_coord":242.0,"y_coord":253.0,"z_coord":0.0,"x_univ":242.0,"y_univ":253.0,"z_univ":0.0,"g_scores":0.0,"h_scores":0.0,"f_scores":0.0,"adjacencies":[{"weight":1.0,"target":1079},{"weight":1.0,"target":1348},{"weight":1.0,"target":1191},{"weight":1.0,"target":1200},{"weight":1.0,"target":1271}]}{"buildingID":5,"toFloor":0,"id":1191,"map_id":18,"x_coord":242.0,"y_coord":256.0,"z_coord":0.0,"x_univ":242.0,"y_univ":256.0,"z_univ":0.0,"g_scores":0.0,"h_scores":0.0,"f_scores":0.0,"adjacencies":[{"weight":1.0,"target":1139},{"weight":1.0,"target":1078},{"weight":1.0,"target":1078},{"weight":1.0,"target":1200},{"weight":1.0,"target":1271},{"weight":1.0,"target":1348}]}{"buildingID":5,"toFloor":0,"id":1200,"map_id":19,"x_coord":242.0,"y_coord":253.0,"z_coord":0.0,"x_univ":242.0,"y_univ":253.0,"z_univ":0.0,"g_scores":0.0,"h_scores":0.0,"f_scores":0.0,"adjacencies":[{"weight":1.0,"target":1204},{"weight":1.0,"target":1078},{"weight":1.0,"target":1191},{"weight":1.0,"target":1271},{"weight":1.0,"target":1348}]}{"buildingID":5,"toFloor":0,"id":1271,"map_id":20,"x_coord":244.0,"y_coord":254.0,"z_coord":0.0,"x_univ":244.0,"y_univ":254.0,"z_univ":0.0,"g_scores":0.0,"h_scores":0.0,"f_scores":0.0,"adjacencies":[{"weight":1.0,"target":1272},{"weight":1.0,"target":1078},{"weight":1.0,"target":1191},{"weight":1.0,"target":1200},{"weight":1.0,"target":1348}]}{"buildingID":5,"toFloor":0,"id":1348,"map_id":16,"x_coord":242.0,"y_coord":256.0,"z_coord":0.0,"x_univ":242.0,"y_univ":256.0,"z_univ":0.0,"g_scores":0.0,"h_scores":0.0,"f_scores":0.0,"adjacencies":[{"weight":1.0,"target":1347},{"weight":1.0,"target":1078},{"weight":1.0,"target":1191},{"weight":1.0,"target":1200},{"weight":1.0,"target":1271}]}{"buildingID":2,"toFloor":1,"id":2115,"map_id":8,"x_coord":515.0,"y_coord":228.0,"z_coord":0.0,"x_univ":515.0,"y_univ":228.0,"z_univ":0.0,"g_scores":0.0,"h_scores":0.0,"f_scores":0.0,"adjacencies":[{"weight":1.0,"target":2114},{"weight":1.0,"target":146},{"weight":1.0,"target":413}]}{"buildingID":4,"toFloor":2,"id":2153,"map_id":13,"x_coord":95.0,"y_coord":227.0,"z_coord":0.0,"x_univ":95.0,"y_univ":227.0,"z_univ":0.0,"g_scores":0.0,"h_scores":0.0,"f_scores":0.0,"adjacencies":[{"weight":1.0,"target":1076},{"weight":1.0,"target":1072},{"weight":1.0,"target":1005}]}